.travis.yml
LICENSE
MANIFEST.in
Makefile
README.md
README.rst
pytest.ini
setup.cfg
setup.py
examples/Makefile
examples/example_active_analyzer.py
examples/example_active_range.py
examples/example_ast_code.py
examples/example_codegen.py
examples/example_controlflow_analyzer.py
examples/example_dataflow_analyzer.py
examples/example_dataflow_codegen.py
examples/example_graphgen.py
examples/example_identifierreplace.py
examples/example_identifiervisitor.py
examples/example_lexer.py
examples/example_merge.py
examples/example_optimizer.py
examples/example_parser.py
examples/example_preprocessor.py
examples/example_subset.py
examples/example_walker.py
img/out.png
img/top_state.png
pyverilog/__init__.py
pyverilog.egg-info/PKG-INFO
pyverilog.egg-info/SOURCES.txt
pyverilog.egg-info/dependency_links.txt
pyverilog.egg-info/requires.txt
pyverilog.egg-info/top_level.txt
pyverilog/ast_code_generator/__init__.py
pyverilog/ast_code_generator/codegen.py
pyverilog/ast_code_generator/touch.py
pyverilog/ast_code_generator/template/__init__.py
pyverilog/ast_code_generator/template/always.txt
pyverilog/ast_code_generator/template/and.txt
pyverilog/ast_code_generator/template/assign.txt
pyverilog/ast_code_generator/template/block.txt
pyverilog/ast_code_generator/template/blockingsubstitution.txt
pyverilog/ast_code_generator/template/case.txt
pyverilog/ast_code_generator/template/casestatement.txt
pyverilog/ast_code_generator/template/casexstatement.txt
pyverilog/ast_code_generator/template/concat.txt
pyverilog/ast_code_generator/template/cond.txt
pyverilog/ast_code_generator/template/constant.txt
pyverilog/ast_code_generator/template/decl.txt
pyverilog/ast_code_generator/template/delaystatement.txt
pyverilog/ast_code_generator/template/description.txt
pyverilog/ast_code_generator/template/disable.txt
pyverilog/ast_code_generator/template/divide.txt
pyverilog/ast_code_generator/template/eq.txt
pyverilog/ast_code_generator/template/eql.txt
pyverilog/ast_code_generator/template/eventstatement.txt
pyverilog/ast_code_generator/template/floatconst.txt
pyverilog/ast_code_generator/template/foreverstatement.txt
