Metadata-Version: 2.1
Name: pyverilog
Version: 1.2.0
Summary: Python-based Hardware Design Processing Toolkit for Verilog HDL: Parser, Dataflow Analyzer, Controlflow Analyzer and Code Generator
Home-page: https://github.com/PyHDI/Pyverilog
Author: Shinya Takamaeda-Yamazaki
License: Apache License 2.0
Keywords: Verilog HDL,Lexer,Parser,Dataflow Analyzer,Control-flow Analyzer,Code Generator,Visualizer
Platform: UNKNOWN
Provides-Extra: test
Provides-Extra: graph
